{
    "genetic_algorithm": {
        "population_size": 100,
        "offspring_count": 50,
        "crossover": {
            "type": "two_point",
            "rate": 0.8
        },
        "mutation": {
            "type": "multigen",
            "rate": 0.02,
            "uniform": true
        },
        "replacement_method": "young_bias",
        "stop_criteria": {
            "max_generations": 100,
            "structure": 0.05,
            "content": 0.05,
            "optimal_fitness": 100
        },
        "character_class": 0,
        "total_points": 200,
        "time_limit": 120,
        "selection": {
            "parents": {
                "method1": "tournament",
                "method2": "elite",
                "method1_proportion": 0.5
            },
            "replacement": {
                "method1": "tournament",
                "method2": "tournament",
                "method1_proportion": 0.5
            },
            "tournament": {
                "type": "probabilistic",
                "m": 5,
                "threshold": 0.75
            },
            "boltzmann": {
                "Tmin": 0.5,
                "Tmax": 2.0,
                "k": 0.1
            }
        }
    },
    "outputName": "C_0_P_tournament_elite_R_tournament_tournament_T_probabilistic"
}